{
	"configurations" : 
	[
		{
			"directories" : 
			[
				{
					"build" : ".",
					"minimumCMakeVersion" : 
					{
						"string" : "3.10"
					},
					"projectIndex" : 0,
					"source" : ".",
					"targetIndexes" : 
					[
						0,
						1
					]
				}
			],
			"name" : "Debug",
			"projects" : 
			[
				{
					"directoryIndexes" : 
					[
						0
					],
					"name" : "yolov11",
					"targetIndexes" : 
					[
						0,
						1
					]
				}
			],
			"targets" : 
			[
				{
					"directoryIndex" : 0,
					"id" : "myplugins::@6890427a1f51a3e7e1df",
					"jsonFile" : "target-myplugins-Debug-abc922f461752c2bf295.json",
					"name" : "myplugins",
					"projectIndex" : 0
				},
				{
					"directoryIndex" : 0,
					"id" : "yolo11_det::@6890427a1f51a3e7e1df",
					"jsonFile" : "target-yolo11_det-Debug-f58a82ab6539d23c11c3.json",
					"name" : "yolo11_det",
					"projectIndex" : 0
				}
			]
		}
	],
	"kind" : "codemodel",
	"paths" : 
	{
		"build" : "/home/zy/yolo11trt/get_model/build",
		"source" : "/home/zy/yolo11trt/get_model"
	},
	"version" : 
	{
		"major" : 2,
		"minor" : 0
	}
}
